[
    {
        "name": "Black-Floral-Tutu-Dress",
        "serialNumber": 12345,
        "price": 1,
        "manufacturer": "CC",
        "cateogory": "clothing",
        "quantity": 1,
        "avaiableUnits": 2
    },
    {
        "name": "Bunny-Ear-Hooded",
        "serialNumber": 23456,
        "price": 1,
        "manufacturer": "CC",
        "cateogory": "clothing",
        "quantity": 1,
        "avaiableUnits": 5
    },
    {
        "name": "Floral-Bloomers",
        "serialNumber": 34567,
        "price": 1,
        "manufacturer": "CC",
        "cateogory": "clothing",
        "quantity": 1,
        "avaiableUnits": 5
    },
    {
        "name": "Floral-Flare-Romper",
        "serialNumber": 45678,
        "price": 1,
        "manufacturer": "CC",
        "cateogory": "clothing",
        "quantity": 1,
        "avaiableUnits": 5
    },
    {
        "name": "Get-It-From-Mama",
        "serialNumber": 56789,
        "price": 1,
        "manufacturer": "CC",
        "cateogory": "clothing",
        "quantity": 1,
        "avaiableUnits": 5
    },
    {
        "name": "Lace-Flare-Sleeve-Dress",
        "serialNumber": 56789,
        "price": 1,
        "manufacturer": "CC",
        "cateogory": "clothing",
        "quantity": 1,
        "avaiableUnits": 5
    },
    {
        "name": "Lemon-Drop-Romper",
        "serialNumber": 56789,
        "price": 1,
        "manufacturer": "CC",
        "cateogory": "clothing",
        "quantity": 1,
        "avaiableUnits": 5
    },
    {
        "name": "Lets-Taco-About-It",
        "serialNumber": 56789,
        "price": 1,
        "manufacturer": "CC",
        "cateogory": "clothing",
        "quantity": 1,
        "avaiableUnits": 5
    },
    {
        "name": "Little-Miss-Sassy-Pants",
        "serialNumber": 56789,
        "price": 1,
        "manufacturer": "CC",
        "cateogory": "clothing",
        "quantity": 1,
        "avaiableUnits": 5
    },
    {
        "name": "My-Prince-is-Daddy",
        "serialNumber": 56789,
        "price": 1,
        "manufacturer": "CC",
        "cateogory": "clothing",
        "quantity": 1,
        "avaiableUnits": 5
    },
    {
        "name": "Polka-Dot",
        "serialNumber": 56789,
        "price": 1,
        "manufacturer": "CC",
        "cateogory": "clothing",
        "quantity": 1,
        "avaiableUnits": 5
    },
    {
        "name": "Priscilla-Petal-Dress",
        "serialNumber": 56789,
        "price": 1,
        "manufacturer": "CC",
        "cateogory": "clothing",
        "quantity": 1,
        "avaiableUnits": 5
    }
]
